<?xml version="1.0" encoding="utf-8" ?>
<?iso-639-1 en?>
<!DOCTYPE procon [
  <!ATTLIST match regex CDATA #IMPLIED>
  <!ATTLIST match text CDATA #IMPLIED>
  <!ATTLIST loc key CDATA #IMPLIED>
  <!ATTLIST loc value CDATA #IMPLIED>
]>
<procon>
  <core>
    <interfaces>
      <connections>
        <plugins>
          <basicingameinfo>
            <loc key="HelpCommand" value="Provides a list of commands available to the player" />
            <loc key="HelpCommandHeader" value="Type '{0}help [command]' for more information about a command:" />
            <loc key="TestCommand" value="Basic command to output the results of a NLP match" />
          </basicingameinfo>
        </plugins>
      </connections>
    </interfaces>
  </core>
</procon>